{
  "sourceLanguage": "en",
  "version": "1.0",
  "strings": {
    "Average Pause": {
      "localizations": {
        "de": {
          "stringUnit": {
            "state": "translated",
            "value": "Durchschnittliche Pause"
          }
        },
        "es": {
          "stringUnit": {
            "state": "translated",
            "value": "Pausa promedio"
          }
        },
        "fr": {
          "stringUnit": {
            "state": "translated",
            "value": "Pause moyenne"
          }
        },
        "hi": {
          "stringUnit": {
            "state": "translated",
            "value": "औसत विराम"
          }
        },
        "id": {
          "stringUnit": {
            "state": "translated",
            "value": "Jeda Rata-rata"
          }
        },
        "it": {
          "stringUnit": {
            "state": "translated",
            "value": "Pausa media"
          }
        },
        "ja": {
          "stringUnit": {
            "state": "translated",
            "value": "平均ポーズ"
          }
        },
        "ko": {
          "stringUnit": {
            "state": "translated",
            "value": "평균 일시 정지"
          }
        },
        "nl": {
          "stringUnit": {
            "state": "translated",
            "value": "Gemiddelde Pauze"
          }
        },
        "pl": {
          "stringUnit": {
            "state": "translated",
            "value": "Średnia przerwa"
          }
        },
        "pt-BR": {
          "stringUnit": {
            "state": "translated",
            "value": "Pausa Média"
          }
        },
        "ru": {
          "stringUnit": {
            "state": "translated",
            "value": "Средняя пауза"
          }
        },
        "th": {
          "stringUnit": {
            "state": "translated",
            "value": "หยุดชั่วคราวเฉลี่ย"
          }
        },
        "tr": {
          "stringUnit": {
            "state": "translated",
            "value": "Ortalama Duraklatma"
          }
        },
        "uk": {
          "stringUnit": {
            "state": "translated",
            "value": "Середній пауза"
          }
        },
        "vi": {
          "stringUnit": {
            "state": "translated",
            "value": "Tạm dừng trung bình"
          }
        },
        "zh-Hans": {
          "stringUnit": {
            "state": "translated",
            "value": "平均暂停"
          }
        },
        "zh-Hant": {
          "stringUnit": {
            "state": "translated",
            "value": "平均暫停"
          }
        }
      }
    }
  }
}