{
  "sourceLanguage": "en",
  "version": "1.0",
  "strings": {
    "Unlock Full Access": {
      "localizations": {
        "de": {
          "stringUnit": {
            "state": "translated",
            "value": "Vollzugriff freischalten"
          }
        },
        "es": {
          "stringUnit": {
            "state": "translated",
            "value": "Desbloquear acceso completo"
          }
        },
        "fr": {
          "stringUnit": {
            "state": "translated",
            "value": "Débloquer l'accès complet"
          }
        },
        "hi": {
          "stringUnit": {
            "state": "translated",
            "value": "पूर्ण पहुंच अनलॉक करें।"
          }
        },
        "id": {
          "stringUnit": {
            "state": "translated",
            "value": "Buka Akses Penuh"
          }
        },
        "it": {
          "stringUnit": {
            "state": "translated",
            "value": "Sblocca l'accesso completo."
          }
        },
        "ja": {
          "stringUnit": {
            "state": "translated",
            "value": "フルアクセスを解除"
          }
        },
        "ko": {
          "stringUnit": {
            "state": "translated",
            "value": "풀 액세스 잠금 해제"
          }
        },
        "nl": {
          "stringUnit": {
            "state": "translated",
            "value": "Ontgrendel volledige toegang"
          }
        },
        "pl": {
          "stringUnit": {
            "state": "translated",
            "value": "Odblokuj pełny dostęp"
          }
        },
        "pt-BR": {
          "stringUnit": {
            "state": "translated",
            "value": "Desbloquear Acesso Completo"
          }
        },
        "ru": {
          "stringUnit": {
            "state": "translated",
            "value": "Разблокировать полный доступ"
          }
        },
        "th": {
          "stringUnit": {
            "state": "translated",
            "value": "ปลดล็อคการเข้าถึงเต็มรูปแบบ"
          }
        },
        "tr": {
          "stringUnit": {
            "state": "translated",
            "value": "Tam Erişimi Açın."
          }
        },
        "uk": {
          "stringUnit": {
            "state": "translated",
            "value": "Розблокувати повний доступ"
          }
        },
        "vi": {
          "stringUnit": {
            "state": "translated",
            "value": "Mở Khóa Truy Cập Đầy Đủ"
          }
        },
        "zh-Hans": {
          "stringUnit": {
            "state": "translated",
            "value": "解锁完整访问"
          }
        },
        "zh-Hant": {
          "stringUnit": {
            "state": "translated",
            "value": "解鎖完整訪問"
          }
        }
      }
    }
  }
}