{
  "sourceLanguage": "en",
  "version": "1.0",
  "strings": {
    "Most Recently Added": {
      "localizations": {
        "de": {
          "stringUnit": {
            "state": "translated",
            "value": "Zuletzt hinzugefügt"
          }
        },
        "es": {
          "stringUnit": {
            "state": "translated",
            "value": "Más recientemente añadido."
          }
        },
        "fr": {
          "stringUnit": {
            "state": "translated",
            "value": "Plus récemment ajouté"
          }
        },
        "hi": {
          "stringUnit": {
            "state": "translated",
            "value": "हाल ही में जोड़ा गया नया"
          }
        },
        "id": {
          "stringUnit": {
            "state": "translated",
            "value": "Baru Ditambahkan Terbaru"
          }
        },
        "it": {
          "stringUnit": {
            "state": "translated",
            "value": "Più recentemente aggiunto."
          }
        },
        "ja": {
          "stringUnit": {
            "state": "translated",
            "value": "最近追加された"
          }
        },
        "ko": {
          "stringUnit": {
            "state": "translated",
            "value": "최근 추가된 것들"
          }
        },
        "nl": {
          "stringUnit": {
            "state": "translated",
            "value": "Meest recent toegevoegd."
          }
        },
        "pl": {
          "stringUnit": {
            "state": "translated",
            "value": "Ostatnio dodane."
          }
        },
        "pt-BR": {
          "stringUnit": {
            "state": "translated",
            "value": "Mais recentemente adicionado."
          }
        },
        "ru": {
          "stringUnit": {
            "state": "translated",
            "value": "Последние добавленные"
          }
        },
        "th": {
          "stringUnit": {
            "state": "translated",
            "value": "เพิ่มล่าสุดที่สุด"
          }
        },
        "tr": {
          "stringUnit": {
            "state": "translated",
            "value": "En Son Eklenenler\""
          }
        },
        "uk": {
          "stringUnit": {
            "state": "translated",
            "value": "Останні додані"
          }
        },
        "vi": {
          "stringUnit": {
            "state": "translated",
            "value": "Gần đây nhấtThêm vào"
          }
        },
        "zh-Hans": {
          "stringUnit": {
            "state": "translated",
            "value": "最近添加"
          }
        },
        "zh-Hant": {
          "stringUnit": {
            "state": "translated",
            "value": "最近新增"
          }
        }
      }
    }
  }
}